{
  "schemaVersion": "1.0",
  "updatedAt": "2026-03-13T16:18:31.090664+00:00",
  "sources": {
    "static_source::static:listing_url:https://www.valvesoftware.com/en/jobs": {
      "lastRunAt": "2026-03-13T16:18:27.939021+00:00",
      "lastStatus": "ok",
      "lastDurationMs": 3220,
      "lastFetchedCount": 28,
      "lastKeptCount": 28,
      "lastCandidateLinksFound": 28,
      "lastDetailPagesVisited": 28,
      "lastDetailYieldPct": 100,
      "lastRedirectCandidates": 0,
      "lastRedirectResolved": 0,
      "lastRedirectCacheHits": 0,
      "lastSuccessAt": "2026-03-13T16:18:27.939021+00:00",
      "lastFingerprint": "a4d0a5b8b3fdd61dc16029318aad62ee22823219",
      "consecutiveFailures": 0,
      "lastStageTimingsMs": {
        "listingFetch": 582,
        "parseCsv": 0,
        "candidateExtraction": 4,
        "detailFetch": 14409,
        "redirectResolve": 0,
        "canonicalization": 3
      }
    },
    "lever_sources": {
      "lastRunAt": "2026-03-13T16:18:27.939021+00:00",
      "lastStatus": "ok",
      "lastDurationMs": 4054,
      "lastFetchedCount": 26,
      "lastKeptCount": 26,
      "lastCandidateLinksFound": 0,
      "lastDetailPagesVisited": 0,
      "lastDetailYieldPct": 0,
      "lastRedirectCandidates": 0,
      "lastRedirectResolved": 0,
      "lastRedirectCacheHits": 0,
      "lastSuccessAt": "2026-03-13T16:18:27.939021+00:00",
      "lastFingerprint": "8dae2c379483efac4f9b076f805cf9ada93c5741",
      "consecutiveFailures": 0,
      "lastStageTimingsMs": {
        "listingFetch": 0,
        "parseCsv": 0,
        "candidateExtraction": 0,
        "detailFetch": 0,
        "redirectResolve": 0,
        "canonicalization": 3
      }
    },
    "remote_ok": {
      "lastRunAt": "2026-03-13T16:18:27.939021+00:00",
      "lastStatus": "ok",
      "lastDurationMs": 632,
      "lastFetchedCount": 47,
      "lastKeptCount": 47,
      "lastCandidateLinksFound": 0,
      "lastDetailPagesVisited": 0,
      "lastDetailYieldPct": 0,
      "lastRedirectCandidates": 0,
      "lastRedirectResolved": 0,
      "lastRedirectCacheHits": 0,
      "lastSuccessAt": "2026-03-13T16:18:27.939021+00:00",
      "lastFingerprint": "e971735ebad79d14f59ef8c7766c527f234a4c90",
      "consecutiveFailures": 0,
      "lastStageTimingsMs": {
        "listingFetch": 0,
        "parseCsv": 0,
        "candidateExtraction": 0,
        "detailFetch": 0,
        "redirectResolve": 0,
        "canonicalization": 5
      }
    },
    "gamesindustry": {
      "lastRunAt": "2026-03-13T16:18:27.939021+00:00",
      "lastStatus": "ok",
      "lastDurationMs": 380,
      "lastFetchedCount": 24,
      "lastKeptCount": 24,
      "lastCandidateLinksFound": 0,
      "lastDetailPagesVisited": 0,
      "lastDetailYieldPct": 0,
      "lastRedirectCandidates": 0,
      "lastRedirectResolved": 0,
      "lastRedirectCacheHits": 0,
      "lastSuccessAt": "2026-03-13T16:18:27.939021+00:00",
      "lastFingerprint": "74cd1da01d74ee993eb7f2f4f8e4bf0989e39a49",
      "consecutiveFailures": 0,
      "lastStageTimingsMs": {
        "listingFetch": 0,
        "parseCsv": 0,
        "candidateExtraction": 0,
        "detailFetch": 0,
        "redirectResolve": 0,
        "canonicalization": 2
      }
    },
    "smartrecruiters_sources": {
      "lastRunAt": "2026-03-13T16:18:27.939021+00:00",
      "lastStatus": "ok",
      "lastDurationMs": 996,
      "lastFetchedCount": 87,
      "lastKeptCount": 87,
      "lastCandidateLinksFound": 0,
      "lastDetailPagesVisited": 0,
      "lastDetailYieldPct": 0,
      "lastRedirectCandidates": 0,
      "lastRedirectResolved": 0,
      "lastRedirectCacheHits": 0,
      "lastSuccessAt": "2026-03-13T16:18:27.939021+00:00",
      "lastFingerprint": "b979db63b221b25ba339b04b37cd15ea1cb72e66",
      "consecutiveFailures": 0,
      "lastStageTimingsMs": {
        "listingFetch": 0,
        "parseCsv": 0,
        "candidateExtraction": 0,
        "detailFetch": 0,
        "redirectResolve": 0,
        "canonicalization": 8
      }
    },
    "google_sheets": {
      "lastRunAt": "2026-03-13T16:18:27.939021+00:00",
      "lastStatus": "ok",
      "lastDurationMs": 83327,
      "lastFetchedCount": 32811,
      "lastKeptCount": 32810,
      "lastCandidateLinksFound": 0,
      "lastDetailPagesVisited": 0,
      "lastDetailYieldPct": 0,
      "lastRedirectCandidates": 449,
      "lastRedirectResolved": 449,
      "lastRedirectCacheHits": 0,
      "lastSuccessAt": "2026-03-13T16:18:27.939021+00:00",
      "lastFingerprint": "1413ac7fe3787bc1fa009e548b5fd977d40abc9d",
      "consecutiveFailures": 0,
      "lastStageTimingsMs": {
        "listingFetch": 0,
        "parseCsv": 718,
        "candidateExtraction": 0,
        "detailFetch": 0,
        "redirectResolve": 76479,
        "canonicalization": 2111
      }
    },
    "ashby_sources": {
      "lastRunAt": "2026-03-13T16:18:27.939021+00:00",
      "lastStatus": "ok",
      "lastDurationMs": 870,
      "lastFetchedCount": 0,
      "lastKeptCount": 0,
      "lastCandidateLinksFound": 0,
      "lastDetailPagesVisited": 0,
      "lastDetailYieldPct": 0,
      "lastRedirectCandidates": 0,
      "lastRedirectResolved": 0,
      "lastRedirectCacheHits": 0,
      "lastSuccessAt": "2026-03-13T16:18:27.939021+00:00",
      "lastFingerprint": "da39a3ee5e6b4b0d3255bfef95601890afd80709",
      "consecutiveFailures": 0
    },
    "personio_sources": {
      "lastRunAt": "2026-03-13T16:18:27.939021+00:00",
      "lastStatus": "ok",
      "lastDurationMs": 11546,
      "lastFetchedCount": 3,
      "lastKeptCount": 0,
      "lastCandidateLinksFound": 0,
      "lastDetailPagesVisited": 0,
      "lastDetailYieldPct": 0,
      "lastRedirectCandidates": 0,
      "lastRedirectResolved": 0,
      "lastRedirectCacheHits": 0,
      "lastSuccessAt": "2026-03-13T16:18:27.939021+00:00",
      "lastFingerprint": "da39a3ee5e6b4b0d3255bfef95601890afd80709",
      "consecutiveFailures": 0
    },
    "greenhouse_boards": {
      "lastRunAt": "2026-03-13T16:18:27.939021+00:00",
      "lastStatus": "ok",
      "lastDurationMs": 1065,
      "lastFetchedCount": 209,
      "lastKeptCount": 209,
      "lastCandidateLinksFound": 0,
      "lastDetailPagesVisited": 0,
      "lastDetailYieldPct": 0,
      "lastRedirectCandidates": 0,
      "lastRedirectResolved": 0,
      "lastRedirectCacheHits": 0,
      "lastSuccessAt": "2026-03-13T16:18:27.939021+00:00",
      "lastFingerprint": "c6bd9ee0e5f2801d6bf70b72704791631a656be6",
      "consecutiveFailures": 0,
      "lastStageTimingsMs": {
        "listingFetch": 0,
        "parseCsv": 0,
        "candidateExtraction": 0,
        "detailFetch": 0,
        "redirectResolve": 0,
        "canonicalization": 22
      }
    },
    "workable_sources": {
      "lastRunAt": "2026-03-13T16:18:27.939021+00:00",
      "lastStatus": "ok",
      "lastDurationMs": 929,
      "lastFetchedCount": 25,
      "lastKeptCount": 25,
      "lastCandidateLinksFound": 0,
      "lastDetailPagesVisited": 0,
      "lastDetailYieldPct": 0,
      "lastRedirectCandidates": 0,
      "lastRedirectResolved": 0,
      "lastRedirectCacheHits": 0,
      "lastSuccessAt": "2026-03-13T16:18:27.939021+00:00",
      "lastFingerprint": "974fd739de9c8583e5b9b67c9bc9724cec1c1a21",
      "consecutiveFailures": 0,
      "lastStageTimingsMs": {
        "listingFetch": 0,
        "parseCsv": 0,
        "candidateExtraction": 0,
        "detailFetch": 0,
        "redirectResolve": 0,
        "canonicalization": 2
      }
    },
    "epic_games_careers": {
      "lastRunAt": "2026-03-13T16:18:27.939021+00:00",
      "lastStatus": "ok",
      "lastDurationMs": 2273,
      "lastFetchedCount": 248,
      "lastKeptCount": 248,
      "lastCandidateLinksFound": 0,
      "lastDetailPagesVisited": 0,
      "lastDetailYieldPct": 0,
      "lastRedirectCandidates": 0,
      "lastRedirectResolved": 0,
      "lastRedirectCacheHits": 0,
      "lastSuccessAt": "2026-03-13T16:18:27.939021+00:00",
      "lastFingerprint": "39bff6e62c234fbcfcb2e992ae55a5a6de0f5b69",
      "consecutiveFailures": 0,
      "lastStageTimingsMs": {
        "listingFetch": 0,
        "parseCsv": 0,
        "candidateExtraction": 0,
        "detailFetch": 0,
        "redirectResolve": 0,
        "canonicalization": 33
      }
    },
    "static_source::static:listing_url:https://www.ioi.dk/careers": {
      "lastRunAt": "2026-03-09T11:12:27.299648+00:00",
      "lastStatus": "ok",
      "lastDurationMs": 3400,
      "lastFetchedCount": 1,
      "lastKeptCount": 1,
      "lastCandidateLinksFound": 0,
      "lastDetailPagesVisited": 0,
      "lastDetailYieldPct": 0,
      "lastRedirectCandidates": 0,
      "lastRedirectResolved": 0,
      "lastRedirectCacheHits": 0,
      "lastSuccessAt": "2026-03-09T11:12:27.299648+00:00",
      "lastFingerprint": "45944bc4237175638911cada32bf223af6ba5c7a",
      "consecutiveFailures": 0
    },
    "static_source::static:listing_url:https://www.nixxes.com/jobs": {
      "lastRunAt": "2026-03-09T11:12:27.299648+00:00",
      "lastStatus": "ok",
      "lastDurationMs": 5011,
      "lastFetchedCount": 2,
      "lastKeptCount": 2,
      "lastCandidateLinksFound": 0,
      "lastDetailPagesVisited": 0,
      "lastDetailYieldPct": 0,
      "lastRedirectCandidates": 0,
      "lastRedirectResolved": 0,
      "lastRedirectCacheHits": 0,
      "lastSuccessAt": "2026-03-09T11:12:27.299648+00:00",
      "lastFingerprint": "08f86dc988b81816f939a1b2f0a4d1a03d9445fc",
      "consecutiveFailures": 0
    },
    "static_source::static:listing_url:https://www.cdprojekt.com/en/careers": {
      "lastRunAt": "2026-03-09T11:12:27.299648+00:00",
      "lastStatus": "ok",
      "lastDurationMs": 2515,
      "lastFetchedCount": 1,
      "lastKeptCount": 1,
      "lastCandidateLinksFound": 0,
      "lastDetailPagesVisited": 0,
      "lastDetailYieldPct": 0,
      "lastRedirectCandidates": 0,
      "lastRedirectResolved": 0,
      "lastRedirectCacheHits": 0,
      "lastSuccessAt": "2026-03-09T11:12:27.299648+00:00",
      "lastFingerprint": "b9d64f20ad18d550f0f50b9b054030ed577bb5f4",
      "consecutiveFailures": 0
    },
    "static_source::static:listing_url:https://www.fingersoft.com/careers": {
      "lastRunAt": "2026-03-09T11:12:27.299648+00:00",
      "lastStatus": "ok",
      "lastDurationMs": 2796,
      "lastFetchedCount": 1,
      "lastKeptCount": 1,
      "lastCandidateLinksFound": 0,
      "lastDetailPagesVisited": 0,
      "lastDetailYieldPct": 0,
      "lastRedirectCandidates": 0,
      "lastRedirectResolved": 0,
      "lastRedirectCacheHits": 0,
      "lastSuccessAt": "2026-03-09T11:12:27.299648+00:00",
      "lastFingerprint": "9f92f44b478169ec6c605d1b99e92bcbf3129ac1",
      "consecutiveFailures": 0
    },
    "static_source::static:listing_url:https://career.paradoxplaza.com": {
      "lastRunAt": "2026-03-09T11:12:27.299648+00:00",
      "lastStatus": "ok",
      "lastDurationMs": 5414,
      "lastFetchedCount": 5,
      "lastKeptCount": 5,
      "lastCandidateLinksFound": 0,
      "lastDetailPagesVisited": 0,
      "lastDetailYieldPct": 0,
      "lastRedirectCandidates": 0,
      "lastRedirectResolved": 0,
      "lastRedirectCacheHits": 0,
      "lastSuccessAt": "2026-03-09T11:12:27.299648+00:00",
      "lastFingerprint": "99be510f2228637d055f28b104631c21e0e3bab0",
      "consecutiveFailures": 0
    },
    "static_source::static:name:little chicken": {
      "lastRunAt": "2026-03-13T16:18:27.939021+00:00",
      "lastStatus": "ok",
      "lastDurationMs": 5914,
      "lastFetchedCount": 4,
      "lastKeptCount": 4,
      "lastCandidateLinksFound": 4,
      "lastDetailPagesVisited": 4,
      "lastDetailYieldPct": 100,
      "lastRedirectCandidates": 0,
      "lastRedirectResolved": 0,
      "lastRedirectCacheHits": 0,
      "lastSuccessAt": "2026-03-13T16:18:27.939021+00:00",
      "lastFingerprint": "dc1457bf9876a222acac406b0298afcf7420a9cd",
      "consecutiveFailures": 0,
      "lastStageTimingsMs": {
        "listingFetch": 2641,
        "parseCsv": 0,
        "candidateExtraction": 8,
        "detailFetch": 5187,
        "redirectResolve": 0,
        "canonicalization": 0
      }
    },
    "static_source::static:listing_url:https://careers.activision.com": {
      "lastRunAt": "2026-03-13T16:18:27.939021+00:00",
      "lastStatus": "ok",
      "lastDurationMs": 649,
      "lastFetchedCount": 0,
      "lastKeptCount": 0,
      "lastCandidateLinksFound": 0,
      "lastDetailPagesVisited": 0,
      "lastDetailYieldPct": 0,
      "lastRedirectCandidates": 0,
      "lastRedirectResolved": 0,
      "lastRedirectCacheHits": 0,
      "lastSuccessAt": "2026-03-13T16:18:27.939021+00:00",
      "lastFingerprint": "da39a3ee5e6b4b0d3255bfef95601890afd80709",
      "consecutiveFailures": 0,
      "lastStageTimingsMs": {
        "listingFetch": 643,
        "parseCsv": 0,
        "candidateExtraction": 6,
        "detailFetch": 0,
        "redirectResolve": 0,
        "canonicalization": 0
      }
    },
    "teamtailor_sources": {
      "lastRunAt": "2026-03-13T16:18:27.939021+00:00",
      "lastStatus": "ok",
      "lastDurationMs": 1419,
      "lastFetchedCount": 20,
      "lastKeptCount": 20,
      "lastCandidateLinksFound": 0,
      "lastDetailPagesVisited": 0,
      "lastDetailYieldPct": 0,
      "lastRedirectCandidates": 0,
      "lastRedirectResolved": 0,
      "lastRedirectCacheHits": 0,
      "lastSuccessAt": "2026-03-13T16:18:27.939021+00:00",
      "lastFingerprint": "4275ea6a863220c04005c0c6fda55f558c0eb5b7",
      "consecutiveFailures": 0,
      "lastStageTimingsMs": {
        "listingFetch": 0,
        "parseCsv": 0,
        "candidateExtraction": 0,
        "detailFetch": 0,
        "redirectResolve": 0,
        "canonicalization": 1
      }
    },
    "static_source::static:listing_url:https://ea.gr8people.com": {
      "lastRunAt": "2026-03-09T11:12:27.299648+00:00",
      "lastStatus": "ok",
      "lastDurationMs": 43509,
      "lastFetchedCount": 20,
      "lastKeptCount": 20,
      "lastCandidateLinksFound": 0,
      "lastDetailPagesVisited": 0,
      "lastDetailYieldPct": 0,
      "lastRedirectCandidates": 0,
      "lastRedirectResolved": 0,
      "lastRedirectCacheHits": 0,
      "lastSuccessAt": "2026-03-09T11:12:27.299648+00:00",
      "lastFingerprint": "27f119d56a9eecd57072d4113ce43538312f981c",
      "consecutiveFailures": 0
    },
    "static_source::static:listing_url:https://www.riotgames.com/en/work-with-us/jobs": {
      "lastRunAt": "2026-03-13T16:18:27.939021+00:00",
      "lastStatus": "ok",
      "lastDurationMs": 44781,
      "lastFetchedCount": 161,
      "lastKeptCount": 161,
      "lastCandidateLinksFound": 161,
      "lastDetailPagesVisited": 161,
      "lastDetailYieldPct": 100,
      "lastRedirectCandidates": 0,
      "lastRedirectResolved": 0,
      "lastRedirectCacheHits": 0,
      "lastSuccessAt": "2026-03-13T16:18:27.939021+00:00",
      "lastFingerprint": "db4bf98b43cbbb499f0a7ffe0ab76e84f3d765e2",
      "consecutiveFailures": 0,
      "lastStageTimingsMs": {
        "listingFetch": 297,
        "parseCsv": 0,
        "candidateExtraction": 12,
        "detailFetch": 262796,
        "redirectResolve": 0,
        "canonicalization": 16
      }
    },
    "wellfound": {
      "lastRunAt": "2026-03-13T16:18:27.939021+00:00",
      "lastStatus": "excluded",
      "lastDurationMs": 0,
      "lastFetchedCount": 0,
      "lastKeptCount": 0,
      "lastCandidateLinksFound": 0,
      "lastDetailPagesVisited": 0,
      "lastDetailYieldPct": 0,
      "lastRedirectCandidates": 0,
      "lastRedirectResolved": 0,
      "lastRedirectCacheHits": 0,
      "consecutiveFailures": 0
    },
    "static_source::auto:00fb61a6597b": {
      "lastRunAt": "2026-03-09T09:20:16.165568+00:00",
      "lastStatus": "ok",
      "lastDurationMs": 3206,
      "lastFetchedCount": 10,
      "lastKeptCount": 10,
      "lastCandidateLinksFound": 0,
      "lastDetailPagesVisited": 0,
      "lastDetailYieldPct": 0,
      "lastRedirectCandidates": 0,
      "lastRedirectResolved": 0,
      "lastRedirectCacheHits": 0,
      "lastSuccessAt": "2026-03-09T09:20:16.165568+00:00",
      "lastFingerprint": "25b594c2c89e6cf3914f4126c3962658a2eb3ecd",
      "consecutiveFailures": 0
    },
    "static_source::static:listing_url:https://www.naconstudiomilan.com/careers": {
      "lastRunAt": "2026-03-13T16:18:27.939021+00:00",
      "lastStatus": "ok",
      "lastDurationMs": 1192,
      "lastFetchedCount": 0,
      "lastKeptCount": 0,
      "lastCandidateLinksFound": 0,
      "lastDetailPagesVisited": 0,
      "lastDetailYieldPct": 0,
      "lastRedirectCandidates": 0,
      "lastRedirectResolved": 0,
      "lastRedirectCacheHits": 0,
      "lastSuccessAt": "2026-03-13T16:18:27.939021+00:00",
      "lastFingerprint": "da39a3ee5e6b4b0d3255bfef95601890afd80709",
      "consecutiveFailures": 0,
      "lastStageTimingsMs": {
        "listingFetch": 1187,
        "parseCsv": 0,
        "candidateExtraction": 5,
        "detailFetch": 0,
        "redirectResolve": 0,
        "canonicalization": 0
      }
    },
    "static_source::static:listing_url:https://supercell.com/en/careers/": {
      "lastRunAt": "2026-03-13T16:18:27.939021+00:00",
      "lastStatus": "ok",
      "lastDurationMs": 2625,
      "lastFetchedCount": 0,
      "lastKeptCount": 0,
      "lastCandidateLinksFound": 0,
      "lastDetailPagesVisited": 0,
      "lastDetailYieldPct": 0,
      "lastRedirectCandidates": 0,
      "lastRedirectResolved": 0,
      "lastRedirectCacheHits": 0,
      "lastSuccessAt": "2026-03-13T16:18:27.939021+00:00",
      "lastFingerprint": "da39a3ee5e6b4b0d3255bfef95601890afd80709",
      "consecutiveFailures": 0,
      "lastStageTimingsMs": {
        "listingFetch": 2594,
        "parseCsv": 0,
        "candidateExtraction": 26,
        "detailFetch": 0,
        "redirectResolve": 0,
        "canonicalization": 0
      }
    },
    "static_source::static:listing_url:https://www.remedygames.com/careers": {
      "lastRunAt": "2026-03-13T16:18:27.939021+00:00",
      "lastStatus": "ok",
      "lastDurationMs": 876,
      "lastFetchedCount": 0,
      "lastKeptCount": 0,
      "lastCandidateLinksFound": 0,
      "lastDetailPagesVisited": 0,
      "lastDetailYieldPct": 0,
      "lastRedirectCandidates": 0,
      "lastRedirectResolved": 0,
      "lastRedirectCacheHits": 0,
      "lastSuccessAt": "2026-03-13T16:18:27.939021+00:00",
      "lastFingerprint": "da39a3ee5e6b4b0d3255bfef95601890afd80709",
      "consecutiveFailures": 0,
      "lastStageTimingsMs": {
        "listingFetch": 862,
        "parseCsv": 0,
        "candidateExtraction": 14,
        "detailFetch": 0,
        "redirectResolve": 0,
        "canonicalization": 0
      }
    },
    "static_source::static:listing_url:https://milestone.it/careers": {
      "lastRunAt": "2026-03-13T16:18:27.939021+00:00",
      "lastStatus": "ok",
      "lastDurationMs": 810,
      "lastFetchedCount": 0,
      "lastKeptCount": 0,
      "lastCandidateLinksFound": 0,
      "lastDetailPagesVisited": 0,
      "lastDetailYieldPct": 0,
      "lastRedirectCandidates": 0,
      "lastRedirectResolved": 0,
      "lastRedirectCacheHits": 0,
      "lastSuccessAt": "2026-03-13T16:18:27.939021+00:00",
      "lastFingerprint": "da39a3ee5e6b4b0d3255bfef95601890afd80709",
      "consecutiveFailures": 0,
      "lastStageTimingsMs": {
        "listingFetch": 777,
        "parseCsv": 0,
        "candidateExtraction": 29,
        "detailFetch": 0,
        "redirectResolve": 0,
        "canonicalization": 0
      }
    },
    "static_source::static:listing_url:https://www.littlechicken.nl/about-us/jobs/": {
      "lastRunAt": "2026-03-13T16:18:27.939021+00:00",
      "lastStatus": "ok",
      "lastDurationMs": 3899,
      "lastFetchedCount": 3,
      "lastKeptCount": 3,
      "lastCandidateLinksFound": 3,
      "lastDetailPagesVisited": 3,
      "lastDetailYieldPct": 100,
      "lastRedirectCandidates": 0,
      "lastRedirectResolved": 0,
      "lastRedirectCacheHits": 0,
      "lastSuccessAt": "2026-03-13T16:18:27.939021+00:00",
      "lastFingerprint": "4c5e988314491922d0df5abe7674047085c7c0ec",
      "consecutiveFailures": 0,
      "lastStageTimingsMs": {
        "listingFetch": 2280,
        "parseCsv": 0,
        "candidateExtraction": 20,
        "detailFetch": 3571,
        "redirectResolve": 0,
        "canonicalization": 0
      }
    },
    "static_source::static:listing_url:https://larian.com/careers": {
      "lastRunAt": "2026-03-13T16:18:27.939021+00:00",
      "lastStatus": "ok",
      "lastDurationMs": 4877,
      "lastFetchedCount": 18,
      "lastKeptCount": 18,
      "lastCandidateLinksFound": 18,
      "lastDetailPagesVisited": 18,
      "lastDetailYieldPct": 100,
      "lastRedirectCandidates": 0,
      "lastRedirectResolved": 0,
      "lastRedirectCacheHits": 0,
      "lastSuccessAt": "2026-03-13T16:18:27.939021+00:00",
      "lastFingerprint": "5a1f1ad3f40b023a6aa218d3dad0f9af60882ce5",
      "consecutiveFailures": 0,
      "lastStageTimingsMs": {
        "listingFetch": 3355,
        "parseCsv": 0,
        "candidateExtraction": 61,
        "detailFetch": 5279,
        "redirectResolve": 0,
        "canonicalization": 1
      }
    },
    "static_source::static:listing_url:https://ioi.dk/careers/": {
      "lastRunAt": "2026-03-13T16:18:27.939021+00:00",
      "lastStatus": "ok",
      "lastDurationMs": 2805,
      "lastFetchedCount": 1,
      "lastKeptCount": 1,
      "lastCandidateLinksFound": 1,
      "lastDetailPagesVisited": 1,
      "lastDetailYieldPct": 100,
      "lastRedirectCandidates": 0,
      "lastRedirectResolved": 0,
      "lastRedirectCacheHits": 0,
      "lastSuccessAt": "2026-03-13T16:18:27.939021+00:00",
      "lastFingerprint": "45944bc4237175638911cada32bf223af6ba5c7a",
      "consecutiveFailures": 0,
      "lastStageTimingsMs": {
        "listingFetch": 2425,
        "parseCsv": 0,
        "candidateExtraction": 56,
        "detailFetch": 317,
        "redirectResolve": 0,
        "canonicalization": 0
      }
    },
    "static_source::static:listing_url:https://jobs.zenimax.com": {
      "lastRunAt": "2026-03-13T16:18:27.939021+00:00",
      "lastStatus": "error",
      "lastDurationMs": 5740,
      "lastFetchedCount": 0,
      "lastKeptCount": 0,
      "lastCandidateLinksFound": 0,
      "lastDetailPagesVisited": 0,
      "lastDetailYieldPct": 0,
      "lastRedirectCandidates": 0,
      "lastRedirectResolved": 0,
      "lastRedirectCacheHits": 0,
      "lastSuccessAt": "2026-03-13T16:09:52.657738+00:00",
      "lastFingerprint": "da39a3ee5e6b4b0d3255bfef95601890afd80709",
      "consecutiveFailures": 1,
      "lastFailureAt": "2026-03-13T16:18:27.939021+00:00",
      "lastError": "static_source::static:listing_url:https://jobs.zenimax.com: static:Zenimax (Manual Website):https://jobs.zenimax.com: HTTP 403 for https://jobs.zenimax.com"
    },
    "static_source::static:listing_url:https://www.kojimaproductions.jp/en/careers": {
      "lastRunAt": "2026-03-13T16:18:27.939021+00:00",
      "lastStatus": "ok",
      "lastDurationMs": 1757,
      "lastFetchedCount": 0,
      "lastKeptCount": 0,
      "lastCandidateLinksFound": 0,
      "lastDetailPagesVisited": 0,
      "lastDetailYieldPct": 0,
      "lastRedirectCandidates": 0,
      "lastRedirectResolved": 0,
      "lastRedirectCacheHits": 0,
      "lastSuccessAt": "2026-03-13T16:18:27.939021+00:00",
      "lastFingerprint": "da39a3ee5e6b4b0d3255bfef95601890afd80709",
      "consecutiveFailures": 0,
      "lastStageTimingsMs": {
        "listingFetch": 1062,
        "parseCsv": 0,
        "candidateExtraction": 4,
        "detailFetch": 0,
        "redirectResolve": 0,
        "canonicalization": 0
      }
    },
    "static_source::static:listing_url:https://www.aweinteractive.com/careers": {
      "lastRunAt": "2026-03-13T16:18:27.939021+00:00",
      "lastStatus": "ok",
      "lastDurationMs": 856,
      "lastFetchedCount": 0,
      "lastKeptCount": 0,
      "lastCandidateLinksFound": 0,
      "lastDetailPagesVisited": 0,
      "lastDetailYieldPct": 0,
      "lastRedirectCandidates": 0,
      "lastRedirectResolved": 0,
      "lastRedirectCacheHits": 0,
      "lastSuccessAt": "2026-03-13T16:18:27.939021+00:00",
      "lastFingerprint": "da39a3ee5e6b4b0d3255bfef95601890afd80709",
      "consecutiveFailures": 0,
      "lastStageTimingsMs": {
        "listingFetch": 853,
        "parseCsv": 0,
        "candidateExtraction": 3,
        "detailFetch": 0,
        "redirectResolve": 0,
        "canonicalization": 0
      }
    },
    "static_source::static:listing_url:https://gamejobs.work/category/environment-artist": {
      "lastRunAt": "2026-03-13T16:18:27.939021+00:00",
      "lastStatus": "ok",
      "lastDurationMs": 1282,
      "lastFetchedCount": 0,
      "lastKeptCount": 0,
      "lastCandidateLinksFound": 0,
      "lastDetailPagesVisited": 0,
      "lastDetailYieldPct": 0,
      "lastRedirectCandidates": 0,
      "lastRedirectResolved": 0,
      "lastRedirectCacheHits": 0,
      "lastSuccessAt": "2026-03-13T16:18:27.939021+00:00",
      "lastFingerprint": "da39a3ee5e6b4b0d3255bfef95601890afd80709",
      "consecutiveFailures": 0,
      "lastStageTimingsMs": {
        "listingFetch": 1270,
        "parseCsv": 0,
        "candidateExtraction": 10,
        "detailFetch": 0,
        "redirectResolve": 0,
        "canonicalization": 0
      }
    },
    "static_source::static:listing_url:https://www.workwithindies.com/careers/angry-mob-games-stylized-environment-artist": {
      "lastRunAt": "2026-03-13T16:18:27.939021+00:00",
      "lastStatus": "ok",
      "lastDurationMs": 445,
      "lastFetchedCount": 0,
      "lastKeptCount": 0,
      "lastCandidateLinksFound": 0,
      "lastDetailPagesVisited": 0,
      "lastDetailYieldPct": 0,
      "lastRedirectCandidates": 0,
      "lastRedirectResolved": 0,
      "lastRedirectCacheHits": 0,
      "lastSuccessAt": "2026-03-13T16:18:27.939021+00:00",
      "lastFingerprint": "da39a3ee5e6b4b0d3255bfef95601890afd80709",
      "consecutiveFailures": 0,
      "lastStageTimingsMs": {
        "listingFetch": 440,
        "parseCsv": 0,
        "candidateExtraction": 4,
        "detailFetch": 0,
        "redirectResolve": 0,
        "canonicalization": 0
      }
    },
    "static_source::static:listing_url:https://careers.wbd.com/global/en/job/r000087820/lead-environment-artist": {
      "lastRunAt": "2026-03-13T16:18:27.939021+00:00",
      "lastStatus": "ok",
      "lastDurationMs": 2691,
      "lastFetchedCount": 2,
      "lastKeptCount": 2,
      "lastCandidateLinksFound": 1,
      "lastDetailPagesVisited": 1,
      "lastDetailYieldPct": 200,
      "lastRedirectCandidates": 0,
      "lastRedirectResolved": 0,
      "lastRedirectCacheHits": 0,
      "lastSuccessAt": "2026-03-13T16:18:27.939021+00:00",
      "lastFingerprint": "4b8525a5f2e57a09e204cc5cd105fdd93428558c",
      "consecutiveFailures": 0,
      "lastStageTimingsMs": {
        "listingFetch": 2287,
        "parseCsv": 0,
        "candidateExtraction": 6,
        "detailFetch": 398,
        "redirectResolve": 0,
        "canonicalization": 0
      }
    },
    "static_source::static:listing_url:https://www.pixelmafia.com/careers": {
      "lastRunAt": "2026-03-13T16:18:27.939021+00:00",
      "lastStatus": "ok",
      "lastDurationMs": 932,
      "lastFetchedCount": 0,
      "lastKeptCount": 0,
      "lastCandidateLinksFound": 0,
      "lastDetailPagesVisited": 0,
      "lastDetailYieldPct": 0,
      "lastRedirectCandidates": 0,
      "lastRedirectResolved": 0,
      "lastRedirectCacheHits": 0,
      "lastSuccessAt": "2026-03-13T16:18:27.939021+00:00",
      "lastFingerprint": "da39a3ee5e6b4b0d3255bfef95601890afd80709",
      "consecutiveFailures": 0,
      "lastStageTimingsMs": {
        "listingFetch": 927,
        "parseCsv": 0,
        "candidateExtraction": 4,
        "detailFetch": 0,
        "redirectResolve": 0,
        "canonicalization": 0
      }
    },
    "static_source::static:listing_url:https://lazyapply.com/jobs/industry/publishing/jobs/environment-artist": {
      "lastRunAt": "2026-03-13T16:18:27.939021+00:00",
      "lastStatus": "ok",
      "lastDurationMs": 14160,
      "lastFetchedCount": 21,
      "lastKeptCount": 21,
      "lastCandidateLinksFound": 26,
      "lastDetailPagesVisited": 26,
      "lastDetailYieldPct": 81,
      "lastRedirectCandidates": 0,
      "lastRedirectResolved": 0,
      "lastRedirectCacheHits": 0,
      "lastSuccessAt": "2026-03-13T16:18:27.939021+00:00",
      "lastFingerprint": "d50b20f769cca8056b2b8f45688e0b6aaba10f4a",
      "consecutiveFailures": 0,
      "lastStageTimingsMs": {
        "listingFetch": 1288,
        "parseCsv": 0,
        "candidateExtraction": 4,
        "detailFetch": 49873,
        "redirectResolve": 0,
        "canonicalization": 5
      }
    },
    "static_source::static:listing_url:https://careers.nintendo.com/jobs": {
      "lastRunAt": "2026-03-13T16:18:27.939021+00:00",
      "lastStatus": "ok",
      "lastDurationMs": 34456,
      "lastFetchedCount": 56,
      "lastKeptCount": 56,
      "lastCandidateLinksFound": 56,
      "lastDetailPagesVisited": 56,
      "lastDetailYieldPct": 100,
      "lastRedirectCandidates": 0,
      "lastRedirectResolved": 0,
      "lastRedirectCacheHits": 0,
      "lastSuccessAt": "2026-03-13T16:18:27.939021+00:00",
      "lastFingerprint": "ee4390bdd8a2fc9c50fe41b51fc6eba8e49b0018",
      "consecutiveFailures": 0,
      "lastStageTimingsMs": {
        "listingFetch": 1203,
        "parseCsv": 0,
        "candidateExtraction": 9,
        "detailFetch": 187699,
        "redirectResolve": 0,
        "canonicalization": 6
      }
    },
    "scrapy_static_sources": {
      "lastRunAt": "2026-03-13T16:18:27.939021+00:00",
      "lastStatus": "ok",
      "lastDurationMs": 0,
      "lastFetchedCount": 0,
      "lastKeptCount": 0,
      "lastCandidateLinksFound": 0,
      "lastDetailPagesVisited": 0,
      "lastDetailYieldPct": 0,
      "lastRedirectCandidates": 0,
      "lastRedirectResolved": 0,
      "lastRedirectCacheHits": 0,
      "lastSuccessAt": "2026-03-13T16:18:27.939021+00:00",
      "lastFingerprint": "da39a3ee5e6b4b0d3255bfef95601890afd80709",
      "consecutiveFailures": 0
    },
    "static_source::static:listing_url:https://www.impactreality.com/careers": {
      "lastRunAt": "2026-03-13T16:18:27.939021+00:00",
      "lastStatus": "ok",
      "lastDurationMs": 601,
      "lastFetchedCount": 0,
      "lastKeptCount": 0,
      "lastCandidateLinksFound": 0,
      "lastDetailPagesVisited": 0,
      "lastDetailYieldPct": 0,
      "lastRedirectCandidates": 0,
      "lastRedirectResolved": 0,
      "lastRedirectCacheHits": 0,
      "lastSuccessAt": "2026-03-13T16:18:27.939021+00:00",
      "lastFingerprint": "da39a3ee5e6b4b0d3255bfef95601890afd80709",
      "consecutiveFailures": 0,
      "lastStageTimingsMs": {
        "listingFetch": 595,
        "parseCsv": 0,
        "candidateExtraction": 5,
        "detailFetch": 0,
        "redirectResolve": 0,
        "canonicalization": 0
      }
    },
    "static_source::static:listing_url:https://digitalbros.com/careers": {
      "lastRunAt": "2026-03-13T16:18:27.939021+00:00",
      "lastStatus": "ok",
      "lastDurationMs": 1529,
      "lastFetchedCount": 0,
      "lastKeptCount": 0,
      "lastCandidateLinksFound": 0,
      "lastDetailPagesVisited": 0,
      "lastDetailYieldPct": 0,
      "lastRedirectCandidates": 0,
      "lastRedirectResolved": 0,
      "lastRedirectCacheHits": 0,
      "lastSuccessAt": "2026-03-13T16:18:27.939021+00:00",
      "lastFingerprint": "da39a3ee5e6b4b0d3255bfef95601890afd80709",
      "consecutiveFailures": 0,
      "lastStageTimingsMs": {
        "listingFetch": 1523,
        "parseCsv": 0,
        "candidateExtraction": 5,
        "detailFetch": 0,
        "redirectResolve": 0,
        "canonicalization": 0
      }
    },
    "static_source::static:listing_url:https://cdprojektred.com/en/jobs": {
      "lastRunAt": "2026-03-13T16:18:27.939021+00:00",
      "lastStatus": "ok",
      "lastDurationMs": 1585,
      "lastFetchedCount": 0,
      "lastKeptCount": 0,
      "lastCandidateLinksFound": 0,
      "lastDetailPagesVisited": 0,
      "lastDetailYieldPct": 0,
      "lastRedirectCandidates": 0,
      "lastRedirectResolved": 0,
      "lastRedirectCacheHits": 0,
      "lastSuccessAt": "2026-03-13T16:18:27.939021+00:00",
      "lastFingerprint": "da39a3ee5e6b4b0d3255bfef95601890afd80709",
      "consecutiveFailures": 0,
      "lastStageTimingsMs": {
        "listingFetch": 1581,
        "parseCsv": 0,
        "candidateExtraction": 4,
        "detailFetch": 0,
        "redirectResolve": 0,
        "canonicalization": 0
      }
    },
    "static_source::static:listing_url:https://34bigthings.com/careers": {
      "lastRunAt": "2026-03-13T16:18:27.939021+00:00",
      "lastStatus": "ok",
      "lastDurationMs": 1457,
      "lastFetchedCount": 0,
      "lastKeptCount": 0,
      "lastCandidateLinksFound": 0,
      "lastDetailPagesVisited": 0,
      "lastDetailYieldPct": 0,
      "lastRedirectCandidates": 0,
      "lastRedirectResolved": 0,
      "lastRedirectCacheHits": 0,
      "lastSuccessAt": "2026-03-13T16:18:27.939021+00:00",
      "lastFingerprint": "da39a3ee5e6b4b0d3255bfef95601890afd80709",
      "consecutiveFailures": 0,
      "lastStageTimingsMs": {
        "listingFetch": 1452,
        "parseCsv": 0,
        "candidateExtraction": 5,
        "detailFetch": 0,
        "redirectResolve": 0,
        "canonicalization": 0
      }
    },
    "static_source::static:listing_url:https://www.ubisoft.com/en-us/company/careers/locations/milan": {
      "lastRunAt": "2026-03-13T16:18:27.939021+00:00",
      "lastStatus": "ok",
      "lastDurationMs": 1329,
      "lastFetchedCount": 0,
      "lastKeptCount": 0,
      "lastCandidateLinksFound": 0,
      "lastDetailPagesVisited": 0,
      "lastDetailYieldPct": 0,
      "lastRedirectCandidates": 0,
      "lastRedirectResolved": 0,
      "lastRedirectCacheHits": 0,
      "lastSuccessAt": "2026-03-13T16:18:27.939021+00:00",
      "lastFingerprint": "da39a3ee5e6b4b0d3255bfef95601890afd80709",
      "consecutiveFailures": 0,
      "lastStageTimingsMs": {
        "listingFetch": 1273,
        "parseCsv": 0,
        "candidateExtraction": 55,
        "detailFetch": 0,
        "redirectResolve": 0,
        "canonicalization": 0
      }
    },
    "static_source::static:listing_url:https://www.quanticdream.com/en/careers": {
      "lastRunAt": "2026-03-13T16:18:27.939021+00:00",
      "lastStatus": "ok",
      "lastDurationMs": 679,
      "lastFetchedCount": 0,
      "lastKeptCount": 0,
      "lastCandidateLinksFound": 0,
      "lastDetailPagesVisited": 0,
      "lastDetailYieldPct": 0,
      "lastRedirectCandidates": 0,
      "lastRedirectResolved": 0,
      "lastRedirectCacheHits": 0,
      "lastSuccessAt": "2026-03-13T16:18:27.939021+00:00",
      "lastFingerprint": "da39a3ee5e6b4b0d3255bfef95601890afd80709",
      "consecutiveFailures": 0,
      "lastStageTimingsMs": {
        "listingFetch": 677,
        "parseCsv": 0,
        "candidateExtraction": 1,
        "detailFetch": 0,
        "redirectResolve": 0,
        "canonicalization": 0
      }
    },
    "static_source::static:listing_url:https://www.rockstargames.com/careers": {
      "lastRunAt": "2026-03-13T16:18:27.939021+00:00",
      "lastStatus": "ok",
      "lastDurationMs": 1143,
      "lastFetchedCount": 0,
      "lastKeptCount": 0,
      "lastCandidateLinksFound": 0,
      "lastDetailPagesVisited": 0,
      "lastDetailYieldPct": 0,
      "lastRedirectCandidates": 0,
      "lastRedirectResolved": 0,
      "lastRedirectCacheHits": 0,
      "lastSuccessAt": "2026-03-13T16:18:27.939021+00:00",
      "lastFingerprint": "da39a3ee5e6b4b0d3255bfef95601890afd80709",
      "consecutiveFailures": 0,
      "lastStageTimingsMs": {
        "listingFetch": 1142,
        "parseCsv": 0,
        "candidateExtraction": 0,
        "detailFetch": 0,
        "redirectResolve": 0,
        "canonicalization": 0
      }
    },
    "static_source::static:listing_url:https://www.stormindgames.com/careers": {
      "lastRunAt": "2026-03-13T16:18:27.939021+00:00",
      "lastStatus": "ok",
      "lastDurationMs": 2253,
      "lastFetchedCount": 0,
      "lastKeptCount": 0,
      "lastCandidateLinksFound": 0,
      "lastDetailPagesVisited": 0,
      "lastDetailYieldPct": 0,
      "lastRedirectCandidates": 0,
      "lastRedirectResolved": 0,
      "lastRedirectCacheHits": 0,
      "lastSuccessAt": "2026-03-13T16:18:27.939021+00:00",
      "lastFingerprint": "da39a3ee5e6b4b0d3255bfef95601890afd80709",
      "consecutiveFailures": 0,
      "lastStageTimingsMs": {
        "listingFetch": 2247,
        "parseCsv": 0,
        "candidateExtraction": 6,
        "detailFetch": 0,
        "redirectResolve": 0,
        "canonicalization": 0
      }
    },
    "static_source::static:listing_url:https://jobs.nintendo.de": {
      "lastRunAt": "2026-03-13T16:18:27.939021+00:00",
      "lastStatus": "ok",
      "lastDurationMs": 1279,
      "lastFetchedCount": 0,
      "lastKeptCount": 0,
      "lastCandidateLinksFound": 0,
      "lastDetailPagesVisited": 0,
      "lastDetailYieldPct": 0,
      "lastRedirectCandidates": 0,
      "lastRedirectResolved": 0,
      "lastRedirectCacheHits": 0,
      "lastSuccessAt": "2026-03-13T16:18:27.939021+00:00",
      "lastFingerprint": "da39a3ee5e6b4b0d3255bfef95601890afd80709",
      "consecutiveFailures": 0,
      "lastStageTimingsMs": {
        "listingFetch": 1279,
        "parseCsv": 0,
        "candidateExtraction": 0,
        "detailFetch": 0,
        "redirectResolve": 0,
        "canonicalization": 0
      }
    },
    "static_source::static:listing_url:https://www.epicgames.com/site/en-us/careers/jobs": {
      "lastRunAt": "2026-03-13T16:18:27.939021+00:00",
      "lastStatus": "excluded",
      "lastDurationMs": 0,
      "lastFetchedCount": 0,
      "lastKeptCount": 0,
      "lastCandidateLinksFound": 0,
      "lastDetailPagesVisited": 0,
      "lastDetailYieldPct": 0,
      "lastRedirectCandidates": 0,
      "lastRedirectResolved": 0,
      "lastRedirectCacheHits": 0,
      "lastSuccessAt": "2026-03-13T14:07:31.153865+00:00",
      "lastFingerprint": "8860c0562432696a304e3cd122b0697da0e5c72e",
      "consecutiveFailures": 3,
      "quarantinedUntilAt": "2026-03-13T19:09:55.749066+00:00",
      "lastFailureAt": "2026-03-13T16:09:52.657738+00:00",
      "lastError": "static_source::static:listing_url:https://www.epicgames.com/site/en-us/careers/jobs: static:Epic Games (Manual Website):https://www.epicgames.com/site/en-US/careers/jobs: HTTP 403 for https://www.epicgames.com/site/en-US/careers/jobs"
    },
    "static_source::static:listing_url:https://www.arkane-studios.com/en/careers": {
      "lastRunAt": "2026-03-13T16:18:27.939021+00:00",
      "lastStatus": "excluded",
      "lastDurationMs": 0,
      "lastFetchedCount": 0,
      "lastKeptCount": 0,
      "lastCandidateLinksFound": 0,
      "lastDetailPagesVisited": 0,
      "lastDetailYieldPct": 0,
      "lastRedirectCandidates": 0,
      "lastRedirectResolved": 0,
      "lastRedirectCacheHits": 0,
      "consecutiveFailures": 3,
      "quarantinedUntilAt": "2026-03-13T16:19:40.841695+00:00",
      "lastFailureAt": "2026-03-13T13:19:37.964725+00:00",
      "lastError": "static_source::static:listing_url:https://www.arkane-studios.com/en/careers: static:Arkane Studios (Manual Website):https://www.arkane-studios.com/en/careers: HTTP 404 for https://www.arkane-studios.com/en/careers"
    },
    "static_source::static:listing_url:http://www.astragon.de/unternehmen/jobs": {
      "lastRunAt": "2026-03-13T16:18:27.939021+00:00",
      "lastStatus": "ok",
      "lastDurationMs": 661,
      "lastFetchedCount": 0,
      "lastKeptCount": 0,
      "lastCandidateLinksFound": 0,
      "lastDetailPagesVisited": 0,
      "lastDetailYieldPct": 0,
      "lastRedirectCandidates": 0,
      "lastRedirectResolved": 0,
      "lastRedirectCacheHits": 0,
      "lastSuccessAt": "2026-03-13T16:18:27.939021+00:00",
      "lastFingerprint": "da39a3ee5e6b4b0d3255bfef95601890afd80709",
      "consecutiveFailures": 0,
      "lastStageTimingsMs": {
        "listingFetch": 658,
        "parseCsv": 0,
        "candidateExtraction": 2,
        "detailFetch": 0,
        "redirectResolve": 0,
        "canonicalization": 0
      }
    },
    "static_source::static:listing_url:http://jobs.andarion-games.com": {
      "lastRunAt": "2026-03-13T16:18:27.939021+00:00",
      "lastStatus": "ok",
      "lastDurationMs": 1792,
      "lastFetchedCount": 0,
      "lastKeptCount": 0,
      "lastCandidateLinksFound": 0,
      "lastDetailPagesVisited": 0,
      "lastDetailYieldPct": 0,
      "lastRedirectCandidates": 0,
      "lastRedirectResolved": 0,
      "lastRedirectCacheHits": 0,
      "lastSuccessAt": "2026-03-13T16:18:27.939021+00:00",
      "lastFingerprint": "da39a3ee5e6b4b0d3255bfef95601890afd80709",
      "consecutiveFailures": 0,
      "lastStageTimingsMs": {
        "listingFetch": 1787,
        "parseCsv": 0,
        "candidateExtraction": 4,
        "detailFetch": 0,
        "redirectResolve": 0,
        "canonicalization": 0
      }
    },
    "static_source::static:listing_url:https://www.articy.com/en/company/jobs/": {
      "lastRunAt": "2026-03-13T16:18:27.939021+00:00",
      "lastStatus": "ok",
      "lastDurationMs": 1199,
      "lastFetchedCount": 0,
      "lastKeptCount": 0,
      "lastCandidateLinksFound": 0,
      "lastDetailPagesVisited": 0,
      "lastDetailYieldPct": 0,
      "lastRedirectCandidates": 0,
      "lastRedirectResolved": 0,
      "lastRedirectCacheHits": 0,
      "lastSuccessAt": "2026-03-13T16:18:27.939021+00:00",
      "lastFingerprint": "da39a3ee5e6b4b0d3255bfef95601890afd80709",
      "consecutiveFailures": 0,
      "lastStageTimingsMs": {
        "listingFetch": 1194,
        "parseCsv": 0,
        "candidateExtraction": 5,
        "detailFetch": 0,
        "redirectResolve": 0,
        "canonicalization": 0
      }
    },
    "static_source::static:listing_url:https://www.augmented-minds.com/de/unternehmen/karriere/": {
      "lastRunAt": "2026-03-13T16:18:27.939021+00:00",
      "lastStatus": "ok",
      "lastDurationMs": 1700,
      "lastFetchedCount": 0,
      "lastKeptCount": 0,
      "lastCandidateLinksFound": 0,
      "lastDetailPagesVisited": 0,
      "lastDetailYieldPct": 0,
      "lastRedirectCandidates": 0,
      "lastRedirectResolved": 0,
      "lastRedirectCacheHits": 0,
      "lastSuccessAt": "2026-03-13T16:18:27.939021+00:00",
      "lastFingerprint": "da39a3ee5e6b4b0d3255bfef95601890afd80709",
      "consecutiveFailures": 0,
      "lastStageTimingsMs": {
        "listingFetch": 1693,
        "parseCsv": 0,
        "candidateExtraction": 6,
        "detailFetch": 0,
        "redirectResolve": 0,
        "canonicalization": 0
      }
    },
    "static_source::static:listing_url:http://www.ahoiii.com/jobs": {
      "lastRunAt": "2026-03-13T16:18:27.939021+00:00",
      "lastStatus": "ok",
      "lastDurationMs": 348,
      "lastFetchedCount": 0,
      "lastKeptCount": 0,
      "lastCandidateLinksFound": 0,
      "lastDetailPagesVisited": 0,
      "lastDetailYieldPct": 0,
      "lastRedirectCandidates": 0,
      "lastRedirectResolved": 0,
      "lastRedirectCacheHits": 0,
      "lastSuccessAt": "2026-03-13T16:18:27.939021+00:00",
      "lastFingerprint": "da39a3ee5e6b4b0d3255bfef95601890afd80709",
      "consecutiveFailures": 0,
      "lastStageTimingsMs": {
        "listingFetch": 339,
        "parseCsv": 0,
        "candidateExtraction": 8,
        "detailFetch": 0,
        "redirectResolve": 0,
        "canonicalization": 0
      }
    },
    "static_source::static:listing_url:https://tequilaworks.com/en/careers": {
      "lastRunAt": "2026-03-13T16:18:27.939021+00:00",
      "lastStatus": "excluded",
      "lastDurationMs": 0,
      "lastFetchedCount": 0,
      "lastKeptCount": 0,
      "lastCandidateLinksFound": 0,
      "lastDetailPagesVisited": 0,
      "lastDetailYieldPct": 0,
      "lastRedirectCandidates": 0,
      "lastRedirectResolved": 0,
      "lastRedirectCacheHits": 0,
      "consecutiveFailures": 3,
      "quarantinedUntilAt": "2026-03-13T16:19:40.841727+00:00",
      "lastFailureAt": "2026-03-13T13:19:37.964725+00:00",
      "lastError": "static_source::static:listing_url:https://tequilaworks.com/en/careers: static:Tequilaworks (Manual Website):https://tequilaworks.com/en/careers: Network error for https://tequilaworks.com/en/careers: timed out"
    },
    "google_sheets_1mvqhxat": {
      "lastRunAt": "2026-03-13T16:18:27.939021+00:00",
      "lastStatus": "ok",
      "lastDurationMs": 1489,
      "lastFetchedCount": 374,
      "lastKeptCount": 374,
      "lastCandidateLinksFound": 0,
      "lastDetailPagesVisited": 0,
      "lastDetailYieldPct": 0,
      "lastRedirectCandidates": 0,
      "lastRedirectResolved": 0,
      "lastRedirectCacheHits": 0,
      "lastSuccessAt": "2026-03-13T16:18:27.939021+00:00",
      "lastFingerprint": "c0a2a53643d8085b4d0774d7c8b6fd53003676b5",
      "consecutiveFailures": 0,
      "lastStageTimingsMs": {
        "listingFetch": 0,
        "parseCsv": 7,
        "candidateExtraction": 0,
        "detailFetch": 0,
        "redirectResolve": 0,
        "canonicalization": 24
      }
    },
    "google_sheets_1er2oaxo": {
      "lastRunAt": "2026-03-13T16:18:27.939021+00:00",
      "lastStatus": "ok",
      "lastDurationMs": 8490,
      "lastFetchedCount": 2252,
      "lastKeptCount": 2239,
      "lastCandidateLinksFound": 0,
      "lastDetailPagesVisited": 0,
      "lastDetailYieldPct": 0,
      "lastRedirectCandidates": 0,
      "lastRedirectResolved": 0,
      "lastRedirectCacheHits": 0,
      "lastSuccessAt": "2026-03-13T16:18:27.939021+00:00",
      "lastFingerprint": "757ccfe5a7f0b30fbd51f90ac4e42d229ee1684c",
      "consecutiveFailures": 0,
      "lastStageTimingsMs": {
        "listingFetch": 0,
        "parseCsv": 54,
        "candidateExtraction": 0,
        "detailFetch": 0,
        "redirectResolve": 0,
        "canonicalization": 139
      }
    },
    "static_source::static:listing_url:https://insomniac.games/careers": {
      "lastRunAt": "2026-03-13T16:18:27.939021+00:00",
      "lastStatus": "ok",
      "lastDurationMs": 1395,
      "lastFetchedCount": 0,
      "lastKeptCount": 0,
      "lastCandidateLinksFound": 0,
      "lastDetailPagesVisited": 0,
      "lastDetailYieldPct": 0,
      "lastRedirectCandidates": 0,
      "lastRedirectResolved": 0,
      "lastRedirectCacheHits": 0,
      "lastSuccessAt": "2026-03-13T16:18:27.939021+00:00",
      "lastFingerprint": "da39a3ee5e6b4b0d3255bfef95601890afd80709",
      "consecutiveFailures": 0,
      "lastStageTimingsMs": {
        "listingFetch": 1394,
        "parseCsv": 0,
        "candidateExtraction": 1,
        "detailFetch": 0,
        "redirectResolve": 0,
        "canonicalization": 0
      }
    }
  }
}